sosia/__init__.py
sosia/classes/__init__.py
sosia/classes/original.py
sosia/classes/scientist.py
sosia/classes/tests/__init__.py
sosia/classes/tests/test_Original.py
sosia/classes/tests/test_Scientist.py
sosia/establishing/__init__.py
sosia/establishing/constants.py
sosia/establishing/database.py
sosia/establishing/fields_sources.py
sosia/establishing/logger.py
sosia/establishing/tests/__init__.py
sosia/establishing/tests/test_fields_sources.py
sosia/processing/__init__.py
sosia/processing/caching.py
sosia/processing/constants.py
sosia/processing/extracting.py
sosia/processing/getting.py
sosia/processing/initializing.py
sosia/processing/querying.py
sosia/processing/utils.py
sosia/processing/tests/__init__.py
sosia/processing/tests/test_caching.py
sosia/processing/tests/test_extracting.py
sosia/processing/tests/test_getting.py
sosia/processing/tests/test_initializing.py
sosia/processing/tests/test_querying.py
sosia/processing/tests/test_utils.py
sosia/utils/__init__.py
sosia/utils/decorators.py
sosia/utils/helpers.py
sosia-1.0.2.dist-info/licenses/LICENSE
sosia-1.0.2.dist-info/METADATA
sosia-1.0.2.dist-info/WHEEL
sosia-1.0.2.dist-info/top_level.txt
sosia-1.0.2.dist-info/RECORD
