Metadata-Version: 2.4
Name: sosia
Version: 1.0.2
Summary: Find control groups for academics in Scopus
Author-email: "Michael E. Rose and Stefano H. Baruffaldi" <Michael.Ernst.Rose@gmail.com>
Maintainer-email: "Michael E. Rose" <Michael.Ernst.Rose@gmail.com>
License: MIT
Project-URL: Homepage, https://github.com/sosia-dev/sosia
Project-URL: Bug Tracker, https://github.com/sosia-dev/sosia/issues
Project-URL: Documentation (stable), https://sosia.readthedocs.io/en/stable/
Project-URL: Documentation (latest), https://sosia.readthedocs.io/en/latest/
Keywords: sosia,control groups,research
Classifier: Development Status :: 4 - Beta
Classifier: Intended Audience :: Science/Research
Classifier: License :: OSI Approved :: MIT License
Classifier: Natural Language :: English
Classifier: Operating System :: OS Independent
Classifier: Programming Language :: Python :: 3.9
Classifier: Programming Language :: Python :: 3.10
Classifier: Programming Language :: Python :: 3.11
Classifier: Programming Language :: Python :: 3.12
Classifier: Topic :: Software Development :: Libraries :: Python Modules
Classifier: Topic :: Scientific/Engineering :: Information Analysis
License-File: LICENSE
Requires-Dist: numpy
Requires-Dist: typing_extensions
Requires-Dist: pandas>=2.1.0
Requires-Dist: pybliometrics>=4.2
Requires-Dist: tqdm
Dynamic: license-file
